auxein/__init__.py
auxein/fitness/__init__.py
auxein/fitness/core.py
auxein/fitness/kernel_based.py
auxein/fitness/observation_based.py
auxein/fitness/utils/__init__.py
auxein/fitness/utils/utils.py
auxein/mutations/__init__.py
auxein/mutations/core.py
auxein/parents/__init__.py
auxein/parents/distributions/__init__.py
auxein/parents/distributions/core.py
auxein/parents/selections/__init__.py
auxein/parents/selections/core.py
auxein/playgrounds/__init__.py
auxein/playgrounds/static.py
auxein/population/__init__.py
auxein/population/core.py
auxein/population/dna_builders.py
auxein/population/genotype.py
auxein/population/individual.py
auxein/recombinations/__init__.py
auxein/recombinations/core.py
auxein/replacements/__init__.py
auxein/replacements/core.py
auxein-0.1.2.dist-info/LICENSE
auxein-0.1.2.dist-info/METADATA
auxein-0.1.2.dist-info/WHEEL
auxein-0.1.2.dist-info/RECORD
